adieu_allianceauth_customizations/__init__.py
adieu_allianceauth_customizations/admin.py
adieu_allianceauth_customizations/app_settings.py
adieu_allianceauth_customizations/apps.py
adieu_allianceauth_customizations/auth_hooks.py
adieu_allianceauth_customizations/models.py
adieu_allianceauth_customizations/tasks.py
adieu_allianceauth_customizations/urls.py
adieu_allianceauth_customizations/views.py
adieu_allianceauth_customizations/locale/.gitkeep
adieu_allianceauth_customizations/static/allianceauth/icons/android-chrome-192x192.png
adieu_allianceauth_customizations/static/allianceauth/icons/android-chrome-512x512.png
adieu_allianceauth_customizations/static/allianceauth/icons/apple-touch-icon.png
adieu_allianceauth_customizations/static/allianceauth/icons/favicon-16x16.png
adieu_allianceauth_customizations/static/allianceauth/icons/favicon-32x32.png
adieu_allianceauth_customizations/static/allianceauth/icons/favicon.ico
adieu_allianceauth_customizations/static/allianceauth/icons/site.webmanifest
adieu_allianceauth_customizations/static/allianceauth/images/br-logo.svg
adieu_allianceauth_customizations/templates/adieu_allianceauth_customizations/bundles/image-auth-logo.html
adieu_allianceauth_customizations/templates/adieu_allianceauth_customizations/menu/menu-logo.html
adieu_allianceauth_customizations/tests/__init__.py
adieu_allianceauth_customizations/tests/test_example.py
adieu_allianceauth_customizations-0.0.9.dist-info/METADATA
adieu_allianceauth_customizations-0.0.9.dist-info/WHEEL
adieu_allianceauth_customizations-0.0.9.dist-info/licenses/LICENSE
adieu_allianceauth_customizations-0.0.9.dist-info/RECORD
